{"chunk_definitions":[{"chunk_id":"csetup_chunk","chunk_label":"setup","document_id":"9D42FED9","expansion_state":0,"options":{"engine":"r","include":false,"label":"setup"},"row":9,"row_count":1,"visible":true},{"chunk_id":"cjud9se4yf102","chunk_label":"library","document_id":"9D42FED9","expansion_state":0,"options":{"engine":"r","label":"library","message":false},"row":21,"row_count":1,"visible":true},{"chunk_id":"c8mw1gjm1mnb1","chunk_label":"conversion","document_id":"9D42FED9","expansion_state":0,"options":{"echo":false,"engine":"r","label":"conversion"},"row":58,"row_count":1,"visible":true},{"chunk_id":"c8kjjk6gokhdl","chunk_label":"unnamed-chunk-2","document_id":"9D42FED9","expansion_state":0,"options":{"engine":"r","label":"unnamed-chunk-1"},"row":66,"row_count":1,"visible":true}],"default_chunk_options":{"echo":true,"error":false},"doc_write_time":1525908845,"working_dir":null}